CHANGES.txt
LICENSE.txt
MANIFEST.in
README.md
requirements.txt
setup.py
bin/convert.py
docs/README.md
mafan/__init__.py
mafan/constants.py
mafan/download_data.py
mafan/encoding.py
mafan/pinyin.py
mafan/text.py
mafan.egg-info/PKG-INFO
mafan.egg-info/SOURCES.txt
mafan.egg-info/dependency_links.txt
mafan.egg-info/requires.txt
mafan.egg-info/top_level.txt
mafan/hanzidentifier/__init__.py
mafan/hanzidentifier/data.py
mafan/hanzidentifier/hanzidentifier.py
mafan/hanzidentifier/test.py
mafan/third_party/__init__.py
mafan/third_party/jianfan/__init__.py
mafan/third_party/jianfan/charsets.py