Metadata-Version: 1.0
Name: mafan
Version: 0.2.10
Summary: A toolbox for working with the Chinese language in Python
Home-page: https://github.com/hermanschaaf/mafan
Author: Herman Schaaf
Author-email: herman@ironzebra.com
License: LICENSE.txt
Platform: UNKNOWN
